{
  "overrides": [
    {
      "node_id": "30b5c2229ebc",
      "domain": "legacy"
    },
    {
      "node_id": "c4e984b2baa4",
      "domain": "legacy"
    },
    {
      "node_id": "c04a00a1c836",
      "domain": "legacy"
    },
    {
      "node_id": "ec086b6fb4b6",
      "domain": "legacy"
    },
    {
      "node_id": "704f57c6d4e6",
      "domain": "legacy"
    },
    {
      "node_id": "704f57c6aed4",
      "domain": "legacy"
    },
    {
      "node_id": "704f57c7109c",
      "domain": "legacy"
    },
    {
      "node_id": "001999661f5f",
      "domain": "ffddorf_dom1"
    },
    {
      "node_id": "0418d60cc889",
      "domain": "ffddorf_dom1"
    },
    {
      "node_id": "c4e984be2eac",
      "domain": "ffddorf_dom1"
    },
    {
      "node_id": "10feedc2408c",
      "domain": "ffddorf_dom2"
    },
    {
      "node_id": "704f57c6bd78",
      "domain": "ffddorf_dom2"
    },
    {
      "node_id": "e8de275fb4a0",
      "domain": "ffddorf_dom4"
    },
    {
      "node_id": "60e327763022",
      "domain": "ffddorf_dom5"
    },
    {
      "node_id": "60e327b80d4a",
      "domain": "ffddorf_dom5"
    },
    {
      "node_id": "60e3278194ec",
      "domain": "ffddorf_dom5"
    },
    {
      "node_id": "60e32781fd62",
      "domain": "ffddorf_dom5"
    },
    {
      "node_id": "50c7bfd8e168",
      "domain": "ffddorf_dom5"
    },
    {
      "node_id": "30b5c2ee48e2",
      "domain": "ffddorf_dom5"
    },
    {
      "node_id": "18a6f759ee34",
      "domain": "ffddorf_dom5"
    },
    {
      "node_id": "8416f9aef176",
      "domain": "ffddorf_dom5"
    },
    {
      "node_id": "a42bb0a22468",
      "domain": "ffddorf_dom5"
    },
    {
      "node_id": "e894f6aab204",
      "domain": "ffddorf_dom8"
    },
    {
      "node_id": "50c7bf168ede",
      "domain": "ffddorf_dom8"
    },
    {
      "node_id": "ffddorf_dom10",
      "domain": "legacy"
    },
    {
      "node_id": "ffddorf_dom10",
      "domain": "legacy"
    },
    {
      "node_id": "d85d4cae38f0",
      "domain": "legacy_neuss"
    },
    {
      "node_id": "0023cd1fec46",
      "domain": "legacy_neuss"
    },
    {
      "node_id": "647002f72d00",
      "domain": "legacy_neuss"
    },
    {
      "node_id": "14cc20cd4ba4",
      "domain": "legacy_neuss"
    },
    {
      "node_id": "90f65272b612",
      "domain": "legacy_neuss"
    },
    {
      "node_id": "60e327e74b94",
      "domain": "legacy_neuss"
    },
    {
      "node_id": "30b5c23e8542",
      "domain": "legacy_neuss"
    },
    {
      "node_id": "8416f99bb2c0",
      "domain": "legacy_neuss"
    },
    {
      "node_id": "60e327c4afd8",
      "domain": "legacy_neuss"
    },
    {
      "node_id": "60e327c4aea8",
      "domain": "legacy_neuss"
    },
    {
      "node_id": "60e327c4b018",
      "domain": "legacy_neuss"
    },
    {
      "node_id": "60e327c4ac1c",
      "domain": "legacy_neuss"
    },
    {
      "node_id": "30b5c26941d5",
      "domain": "legacy_neuss"
    },
    {
      "node_id": "687251643188",
      "domain": "legacy_neuss"
    },
    {
      "node_id": "60e327c4aefc",
      "domain": "legacy_neuss"
    },
    {
      "node_id": "30b5c23e847c",
      "domain": "legacy_neuss"
    },
    {
      "node_id": "30b5c2b04ef4",
      "domain": "legacy_neuss"
    },
    {
      "node_id": "14cc20b96964",
      "domain": "legacy_neuss"
    },
    {
      "node_id": "8416f9e8d1ec",
      "domain": "legacy_neuss"
    },
    {
      "node_id": "c46e1ffed2b6",
      "domain": "legacy_neuss"
    },
    {
      "node_id": "30b5c2885f96",
      "domain": "ffneuss_dom0"
    },
    {
      "node_id": "30b5c20ea3b4",
      "domain": "ffneuss_dom0"
    },
    {
      "node_id": "8416f9e89084",
      "domain": "ffneuss_dom0"
    },
    {
      "node_id": "14cc20cd1e5e",
      "domain": "ffneuss_dom0"
    },
    {
      "node_id": "c4e984f7c7a6",
      "domain": "ffneuss_dom0"
    },
    {
      "node_id": "ec086b8ad2ca",
      "domain": "ffneuss_dom5"
    }
  ]
}
